mai_bias/__init__.py
mai_bias/bias.py
mai_bias/backend/__init__.py
mai_bias/backend/catalogue_loaders.py
mai_bias/backend/loaders.py
mai_bias/backend/registry.py
mai_bias/catalogue/__init__.py
mai_bias/catalogue/dataset_loaders/__init__.py
mai_bias/catalogue/dataset_loaders/auto_csv.py
mai_bias/catalogue/dataset_loaders/custom_csv.py
mai_bias/catalogue/dataset_loaders/data_csv_rankings.py
mai_bias/catalogue/dataset_loaders/data_researchers.py
mai_bias/catalogue/dataset_loaders/graph.py
mai_bias/catalogue/dataset_loaders/image_pairs.py
mai_bias/catalogue/dataset_loaders/images.py
mai_bias/catalogue/dataset_loaders/uci_csv.py
mai_bias/catalogue/metrics/__init__.py
mai_bias/catalogue/metrics/augmentation_report.py
mai_bias/catalogue/metrics/bias_scan.py
mai_bias/catalogue/metrics/image_bias_analysis.py
mai_bias/catalogue/metrics/interactive_report.py
mai_bias/catalogue/metrics/model_card.py
mai_bias/catalogue/metrics/multi_objective_report.py
mai_bias/catalogue/metrics/networks_layouts.py
mai_bias/catalogue/metrics/optimal_transport.py
mai_bias/catalogue/metrics/ranking_fairness.py
mai_bias/catalogue/metrics/sklearn_audit.py
mai_bias/catalogue/metrics/xai_analysis.py
mai_bias/catalogue/metrics/xai_analysis_embeddings.py
mai_bias/catalogue/model_loaders/__init__.py
mai_bias/catalogue/model_loaders/compute_rankings.py
mai_bias/catalogue/model_loaders/compute_researcher_ranking.py
mai_bias/catalogue/model_loaders/fair_node_ranking.py
mai_bias/catalogue/model_loaders/no_model.py
mai_bias/catalogue/model_loaders/onnx.py
mai_bias/catalogue/model_loaders/onnx_ensemble.py
mai_bias/catalogue/model_loaders/pytorch.py
mai_bias/catalogue/model_loaders/pytorch2onnx.py
mai_bias/states/__init__.py
mai_bias/states/dashboard.py
mai_bias/states/results.py
mai_bias/states/step.py
mai_bias/states/style.py
mai_bias/states/steps/__init__.py
mai_bias/states/steps/analysis.py
mai_bias/states/steps/dataset.py
mai_bias/states/steps/model.py
mai_biasmammoth_commons-0.1.14.dist-info/licenses/LICENSE
mammoth_commons/__init__.py
mai_biasmammoth_commons-0.1.14.dist-info/METADATA
mai_biasmammoth_commons-0.1.14.dist-info/WHEEL
mai_biasmammoth_commons-0.1.14.dist-info/top_level.txt
mai_biasmammoth_commons-0.1.14.dist-info/RECORD
