Metadata-Version: 2.4
Name: MAI-Biasmammoth_commons
Version: 0.1.14
Summary: Desktop app version of the MAI-Bias toolkit.
Home-page: https://github.com/mammoth-eu/mammoth-commons
Author: Emmanouil (Manios) Krasanakis
Author-email: maniospas@hotmail.com
Classifier: Programming Language :: Python :: 3
Classifier: License :: OSI Approved :: MIT License
Classifier: Operating System :: OS Independent
License-File: LICENSE
Requires-Dist: mammoth-commons[all]
Dynamic: author
Dynamic: author-email
Dynamic: classifier
Dynamic: description
Dynamic: description-content-type
Dynamic: home-page
Dynamic: license-file
Dynamic: requires-dist
Dynamic: summary
